<annotation>
  <folder>images</folder>
  <filename>000103.png</filename>
  <segmented>0</segmented>
  <size>
    <width>900</width>
    <height>506</height>
    <depth>3</depth>
  </size>
  <object>
    <name>IRONMAN</name>
    <pose>Unsecified</pose>
    <truncated>0</truncated>
    <difficult>0</difficult>
    <bndbox>
      <xmin>458</xmin>
      <ymin>15</ymin>
      <xmax>825</xmax>
      <ymax>498</ymax>
    </bndbox>
  </object>
  <object>
    <name>IRONMAN</name>
    <pose>Unsecified</pose>
    <truncated>0</truncated>
    <difficult>0</difficult>
    <bndbox>
      <xmin>95</xmin>
      <ymin>3</ymin>
      <xmax>498</xmax>
      <ymax>485</ymax>
    </bndbox>
  </object>
</annotation>
