<annotation>
  <folder>images</folder>
  <filename>000469.png</filename>
  <segmented>0</segmented>
  <size>
    <width>2560</width>
    <height>1600</height>
    <depth>3</depth>
  </size>
  <object>
    <name>IRONMAN</name>
    <pose>Unsecified</pose>
    <truncated>0</truncated>
    <difficult>0</difficult>
    <bndbox>
      <xmin>1878</xmin>
      <ymin>384</ymin>
      <xmax>2213</xmax>
      <ymax>1107</ymax>
    </bndbox>
  </object>
  <object>
    <name>IRONMAN</name>
    <pose>Unsecified</pose>
    <truncated>0</truncated>
    <difficult>0</difficult>
    <bndbox>
      <xmin>1878</xmin>
      <ymin>384</ymin>
      <xmax>2213</xmax>
      <ymax>1107</ymax>
    </bndbox>
  </object>
  <object>
    <name>IRONMAN</name>
    <pose>Unsecified</pose>
    <truncated>0</truncated>
    <difficult>0</difficult>
    <bndbox>
      <xmin>1341</xmin>
      <ymin>410</ymin>
      <xmax>1790</xmax>
      <ymax>1153</ymax>
    </bndbox>
  </object>
</annotation>
